HISTORY.rst
celery_slack/__init__.py
celery_slack/_version.py
celery_slack/attachments.py
celery_slack/callbacks.py
celery_slack/exceptions.py
celery_slack/slack.py
celery_slack/slackify.py
celery_slack-0.4.1.dist-info/LICENSE.txt
celery_slack-0.4.1.dist-info/WHEEL
celery_slack-0.4.1.dist-info/METADATA
celery_slack-0.4.1.dist-info/RECORD
