Metadata-Version: 2.1
Name: celery-slack
Version: 0.4.1
Summary: A Slack extension for Celery.
Home-page: https://github.com/crflynn/celery-slack
License: MIT
Keywords: celery,slack
Author: Christopher Flynn
Author-email: crf204@gmail.com
Requires-Python: >=2.7, !=3.0.*, !=3.1.*, !=3.2.*, !=3.3.*, !=3.4.*
Classifier: Development Status :: 3 - Alpha
Classifier: License :: OSI Approved :: MIT License
Classifier: Natural Language :: English
Classifier: Programming Language :: Python :: 2
Classifier: Programming Language :: Python :: 2.7
Classifier: Programming Language :: Python :: 3
Classifier: Programming Language :: Python :: 3.5
Classifier: Programming Language :: Python :: 3.6
Classifier: Programming Language :: Python :: 3.7
Classifier: Programming Language :: Python :: Implementation :: CPython
Classifier: Topic :: System :: Logging
Classifier: Topic :: System :: Monitoring
Requires-Dist: celery (>=3.1,<5.0)
Requires-Dist: ephem (>=3.7,<4.0)
Requires-Dist: requests (>=2.22,<3.0)
Project-URL: Repository, https://github.com/crflynn/celery-slack
